gjdutils/__init__.py
gjdutils/__version__.py
gjdutils/audios.py
gjdutils/caching.py
gjdutils/cmd.py
gjdutils/colab.py
gjdutils/collection_utils.py
gjdutils/decorators.py
gjdutils/dicts.py
gjdutils/dsci.py
gjdutils/dt.py
gjdutils/env.py
gjdutils/errors.py
gjdutils/files.py
gjdutils/functions.py
gjdutils/google_translate.py
gjdutils/hashing.py
gjdutils/html.py
gjdutils/image_utils.py
gjdutils/indexing.py
gjdutils/iterfunc.py
gjdutils/jsons.py
gjdutils/lists.py
gjdutils/llm_utils.py
gjdutils/llms_claude.py
gjdutils/llms_openai.py
gjdutils/misc.py
gjdutils/num.py
gjdutils/outloud_text_to_speech.py
gjdutils/print_utils.py
gjdutils/prompt_templates.py
gjdutils/pypi_build.py
gjdutils/pytest_utils.py
gjdutils/rand.py
gjdutils/regex.py
gjdutils/runtime.py
gjdutils/sets.py
gjdutils/shell.py
gjdutils/stopwatch.py
gjdutils/strings.py
gjdutils/typ.py
gjdutils/voice_speechrecognition.py
gjdutils/web.py
gjdutils/cli/__init__.py
gjdutils/cli/check_git_clean.py
gjdutils/cli/install_all_dev_dependencies.py
gjdutils/cli/main.py
gjdutils/cli/pypi/__init__.py
gjdutils/cli/pypi/app.py
gjdutils/cli/pypi/check.py
gjdutils/cli/pypi/deploy.py
gjdutils/obsolete/google_text_to_speech.py
gjdutils/obsolete/llms_obsolete.py
gjdutils/scripts/__init__.py
gjdutils/scripts/export_envs.sh
gjdutils/scripts/install.py
gjdutils/todo/convert_parquet.py
gjdutils-0.6.1.data/data/bin/export_envs.sh
gjdutils-0.6.1.dist-info/METADATA
gjdutils-0.6.1.dist-info/WHEEL
gjdutils-0.6.1.dist-info/entry_points.txt
gjdutils-0.6.1.dist-info/licenses/LICENSE
gjdutils-0.6.1.dist-info/RECORD
