Metadata-Version: 2.4
Name: GJDutils
Version: 0.6.1
Summary: A collection of useful utility functions (basics, data science/AI, web development, etc)
Project-URL: Homepage, https://github.com/gregdetre/gjdutils
Project-URL: Repository, https://github.com/gregdetre/gjdutils
Author-email: Greg Detre <greg@gregdetre.com>
License-File: LICENSE
Keywords: ai,data science,dates,llm,strings,utilities,web development
Classifier: Development Status :: 4 - Beta
Classifier: Intended Audience :: Developers
Classifier: License :: OSI Approved :: MIT License
Classifier: Operating System :: OS Independent
Classifier: Programming Language :: Python :: 3
Classifier: Topic :: Utilities
Requires-Python: >=3.10
Requires-Dist: ipython
Requires-Dist: jinja2
Requires-Dist: pydantic
Requires-Dist: python-dotenv
Requires-Dist: rich
Requires-Dist: typer
Provides-Extra: all-no-dev
Requires-Dist: anthropic; extra == 'all-no-dev'
Requires-Dist: azure-cognitiveservices-speech; extra == 'all-no-dev'
Requires-Dist: bs4; extra == 'all-no-dev'
Requires-Dist: elevenlabs>=2.1.0; extra == 'all-no-dev'
Requires-Dist: google-cloud-texttospeech; extra == 'all-no-dev'
Requires-Dist: google-cloud-translate; extra == 'all-no-dev'
Requires-Dist: humanize; extra == 'all-no-dev'
Requires-Dist: lxml; extra == 'all-no-dev'
Requires-Dist: numpy; extra == 'all-no-dev'
Requires-Dist: openai; extra == 'all-no-dev'
Requires-Dist: openai-whisper; extra == 'all-no-dev'
Requires-Dist: pandas; extra == 'all-no-dev'
Requires-Dist: pendulum; extra == 'all-no-dev'
Requires-Dist: pillow; extra == 'all-no-dev'
Requires-Dist: playsound; extra == 'all-no-dev'
Requires-Dist: pyaudio; extra == 'all-no-dev'
Requires-Dist: pygame; extra == 'all-no-dev'
Requires-Dist: python-vlc; extra == 'all-no-dev'
Requires-Dist: speechrecognition; extra == 'all-no-dev'
Provides-Extra: audio-lang
Requires-Dist: azure-cognitiveservices-speech; extra == 'audio-lang'
Requires-Dist: elevenlabs>=2.1.0; extra == 'audio-lang'
Requires-Dist: google-cloud-texttospeech; extra == 'audio-lang'
Requires-Dist: google-cloud-translate; extra == 'audio-lang'
Requires-Dist: openai-whisper; extra == 'audio-lang'
Requires-Dist: playsound; extra == 'audio-lang'
Requires-Dist: pyaudio; extra == 'audio-lang'
Requires-Dist: pygame; extra == 'audio-lang'
Requires-Dist: python-vlc; extra == 'audio-lang'
Requires-Dist: speechrecognition; extra == 'audio-lang'
Provides-Extra: dev
Requires-Dist: black; extra == 'dev'
Requires-Dist: build; extra == 'dev'
Requires-Dist: flake8; extra == 'dev'
Requires-Dist: pytest; extra == 'dev'
Requires-Dist: rich; extra == 'dev'
Requires-Dist: twine; extra == 'dev'
Requires-Dist: typer; extra == 'dev'
Requires-Dist: wheel; extra == 'dev'
Provides-Extra: dsci
Requires-Dist: numpy; extra == 'dsci'
Requires-Dist: pandas; extra == 'dsci'
Provides-Extra: dt
Requires-Dist: humanize; extra == 'dt'
Requires-Dist: pendulum; extra == 'dt'
Provides-Extra: html-web
Requires-Dist: bs4; extra == 'html-web'
Requires-Dist: lxml; extra == 'html-web'
Provides-Extra: llm
Requires-Dist: anthropic; extra == 'llm'
Requires-Dist: openai; extra == 'llm'
Requires-Dist: pillow; extra == 'llm'
